cuttlepy/__init__.py
cuttlepy/client.py
cuttlepy/methods.py
cuttlepy/response.py
cuttlepy-0.2.2.dist-info/METADATA
cuttlepy-0.2.2.dist-info/WHEEL
cuttlepy-0.2.2.dist-info/licenses/LICENSE
cuttlepy-0.2.2.dist-info/RECORD
