Metadata-Version: 2.4
Name: cuttlepy
Version: 0.2.2
Summary: Typed python HTTP client wrapper for PRIMP
Project-URL: Homepage, https://github.com/chanpreet3000/cuttlepy
Project-URL: Bug Tracker, https://github.com/chanpreet3000/cuttlepy/issues
Project-URL: Source Code, https://github.com/chanpreet3000/cuttlepy
Author-email: Chanpreet Singh <chanpreet3000@gmail.com>
License-File: LICENSE
Keywords: aiohttp,client,http,httpx,primp,requests,wrapper
Classifier: Development Status :: 3 - Alpha
Classifier: Intended Audience :: Developers
Classifier: License :: OSI Approved :: MIT License
Classifier: Operating System :: OS Independent
Classifier: Programming Language :: Python :: 3
Classifier: Programming Language :: Python :: 3.8
Classifier: Programming Language :: Python :: 3.9
Classifier: Programming Language :: Python :: 3.10
Classifier: Programming Language :: Python :: 3.11
Classifier: Topic :: Internet :: WWW/HTTP
Classifier: Topic :: Software Development :: Libraries :: Python Modules
Requires-Python: >=3.8
Requires-Dist: primp==0.9.1
